src/__init__.py
src/main.py
src/classes/__init__.py
src/classes/address.py
src/classes/address_book.py
src/classes/birthday.py
src/classes/email.py
src/classes/field.py
src/classes/note.py
src/classes/notes_book.py
src/classes/phone.py
src/classes/record.py
src/constants/__init__.py
src/constants/commands.py
src/utils/__init__.py
src/utils/utils.py
goit_phone_book_bot-0.2.2.dist-info/LICENSE
goit_phone_book_bot-0.2.2.dist-info/METADATA
goit_phone_book_bot-0.2.2.dist-info/WHEEL
goit_phone_book_bot-0.2.2.dist-info/entry_points.txt
goit_phone_book_bot-0.2.2.dist-info/top_level.txt
goit_phone_book_bot-0.2.2.dist-info/RECORD
