Metadata-Version: 2.1
Name: goit-phone-book-bot
Version: 0.2.2
Summary: Phone Book bot developed by team #5 - CREATORS
Home-page: https://github.com/VasylMartyniv/GoIT_Phone_Book_bot
Author: Vasyl Martyniv
Author-email: doc.people97@gmail.com
Classifier: Programming Language :: Python :: 3
Classifier: License :: OSI Approved :: MIT License
Classifier: Operating System :: OS Independent
Requires-Python: >=3.6
License-File: LICENSE
Requires-Dist: pyreadline3
Requires-Dist: tabulate
